MANIFEST.in
requirements.txt
setup.py
timingsclient/__init__.py
timingsclient/perf.py
timingsclient.egg-info/PKG-INFO
timingsclient.egg-info/SOURCES.txt
timingsclient.egg-info/dependency_links.txt
timingsclient.egg-info/requires.txt
timingsclient.egg-info/top_level.txt