Metadata-Version: 1.0
Name: timingsclient
Version: 1.0.2
Summary: Python client for the timings API (see https://github.com/godaddy/timings)
Home-page: https://github.com/godaddy/timings-client-py
Author: GoDaddy Operating Company, LLC
Author-email: mverkerk@godaddy.com
License: MIT
Platform: UNKNOWN
